stringstandard/__init__.py
stringstandard/stringstd.py
devops_trabalho-0.0.4.dist-info/LICENSE
devops_trabalho-0.0.4.dist-info/METADATA
devops_trabalho-0.0.4.dist-info/WHEEL
devops_trabalho-0.0.4.dist-info/top_level.txt
devops_trabalho-0.0.4.dist-info/RECORD
