Metadata-Version: 2.1
Name: devops-trabalho
Version: 0.0.4
Summary: A small example package
Author-email: Carlos Werly <werlyrocha@gmail.com>
Project-URL: Homepage, https://github.com/werlyrocha/devops
Project-URL: Bug Tracker, https://github.com/werlyrocha/devops/issues
Classifier: Programming Language :: Python :: 3
Classifier: License :: OSI Approved :: MIT License
Classifier: Operating System :: OS Independent
Requires-Python: >=3.9
License-File: LICENSE
Requires-Dist: unidecode (==1.3.6)
Requires-Dist: pytest (==7.3.2)
Requires-Dist: flake8 (==6.0.0)
Requires-Dist: build (==0.10.0)
Requires-Dist: twine (==4.0.2)
